setup.cfg
setup.py
jimobama_dispatchers/__init__.py
jimobama_dispatchers/dispatcher.py
jimobama_dispatchers/dispatcherbase.py
jimobama_dispatchers/dispatcherobject.py
jimobama_dispatchers/dispatcheroperation.py
jimobama_dispatchers/dispatcherqueue.py
jimobama_dispatchers/testwritefilequeue.py
jimobama_dispatchers/timers.py
jimobama_dispatchers.egg-info/PKG-INFO
jimobama_dispatchers.egg-info/SOURCES.txt
jimobama_dispatchers.egg-info/dependency_links.txt
jimobama_dispatchers.egg-info/requires.txt
jimobama_dispatchers.egg-info/top_level.txt